lenexpy/__init__.py
lenexpy/decoder/__init__.py
lenexpy/decoder/decoder.py
lenexpy/decoder/encoder.py
lenexpy/decoder/lef_decoder.py
lenexpy/decoder/lef_encoder.py
lenexpy/decoder/lxf_decoder.py
lenexpy/decoder/lxf_encoder.py
lenexpy/models/__init__.py
lenexpy/models/_bootstrap.py
lenexpy/models/agedate.py
lenexpy/models/agegroup.py
lenexpy/models/athelete.py
lenexpy/models/bank.py
lenexpy/models/base.py
lenexpy/models/club.py
lenexpy/models/common.py
lenexpy/models/constructor.py
lenexpy/models/contact.py
lenexpy/models/course.py
lenexpy/models/currency.py
lenexpy/models/entry.py
lenexpy/models/event.py
lenexpy/models/facility.py
lenexpy/models/fee.py
lenexpy/models/gender.py
lenexpy/models/handicap.py
lenexpy/models/heat.py
lenexpy/models/judge.py
lenexpy/models/lenex.py
lenexpy/models/meet.py
lenexpy/models/meetinfoentry.py
lenexpy/models/meetinforecord.py
lenexpy/models/nation.py
lenexpy/models/official.py
lenexpy/models/pointtable.py
lenexpy/models/pool.py
lenexpy/models/qualify.py
lenexpy/models/ranking.py
lenexpy/models/record.py
lenexpy/models/recordlist.py
lenexpy/models/relaymeet.py
lenexpy/models/relayposition.py
lenexpy/models/relayrecord.py
lenexpy/models/result.py
lenexpy/models/session.py
lenexpy/models/split.py
lenexpy/models/stroke.py
lenexpy/models/swimstyle.py
lenexpy/models/swimtime.py
lenexpy/models/timestandard.py
lenexpy/models/timestandardlist.py
lenexpy/models/timestandardref.py
lenexpy/models/timing.py
lenexpy/models_st/__init__.py
lenexpy/models_st/athelete.py
lenexpy/models_st/entry.py
lenexpy/models_st/heat.py
lenexpy/models_st/result.py
lenexpy/strenum.py
lenexpy-3.0.3.dist-info/METADATA
lenexpy-3.0.3.dist-info/WHEEL
lenexpy-3.0.3.dist-info/RECORD
