Metadata-Version: 2.4
Name: lenexpy
Version: 3.0.3
Summary: 
Author: LordCode
Author-email: 9999269010dddd@gmail.com
Requires-Python: >=3.11
Classifier: Programming Language :: Python :: 3
Classifier: Programming Language :: Python :: 3.11
Classifier: Programming Language :: Python :: 3.12
Classifier: Programming Language :: Python :: 3.13
Classifier: Programming Language :: Python :: 3.14
Requires-Dist: lxml (>=6.0.2,<7.0.0)
Requires-Dist: pydantic-xml (>=2.18.0,<3.0.0)
